{"nodes": [{"id": "home_nima_neos_tools_gen_build_conf_sh", "label": "gen-build-conf.sh", "file_type": "code", "source_file": "tools/gen-build-conf.sh", "source_location": "L1", "metadata": {"language": "bash", "kind": "file"}}, {"id": "home_nima_neos_tools_gen_build_conf_sh__entry", "label": "gen-build-conf.sh script", "file_type": "code", "source_file": "tools/gen-build-conf.sh", "source_location": "L1", "metadata": {"language": "bash", "kind": "bash_entrypoint"}}, {"id": "home_nima_neos_tools_gen_build_conf_path", "label": "PATH", "file_type": "code", "source_file": "tools/gen-build-conf.sh", "source_location": "L14", "metadata": {"language": "bash", "kind": "code"}}], "edges": [{"source": "home_nima_neos_tools_gen_build_conf_sh", "target": "home_nima_neos_tools_gen_build_conf_sh__entry", "relation": "contains", "confidence": "EXTRACTED", "source_file": "tools/gen-build-conf.sh", "source_location": "L1", "weight": 1.0}, {"source": "home_nima_neos_tools_gen_build_conf_sh", "target": "home_nima_neos_tools_gen_build_conf_path", "relation": "defines", "confidence": "EXTRACTED", "source_file": "tools/gen-build-conf.sh", "source_location": "L14", "weight": 1.0}]}